code_embedder/__init__.py
code_embedder/code_embedding.py
code_embedder/log_level.py
code_embedder/main.py
code_embedder/script_content_reader.py
code_embedder/script_metadata.py
code_embedder/script_metadata_extractor.py
code_embedder-1.1.3.dist-info/LICENSE
code_embedder-1.1.3.dist-info/METADATA
code_embedder-1.1.3.dist-info/WHEEL
code_embedder-1.1.3.dist-info/entry_points.txt
code_embedder-1.1.3.dist-info/RECORD
