Metadata-Version: 2.1
Name: code-embedder
Version: 1.1.3
Summary: Embed python code from script to markdown
License: MIT
Author: Katerina Vankova
Author-email: katerinavankova1@gmail.com
Requires-Python: >=3.9,<4.0
Classifier: License :: OSI Approved :: MIT License
Classifier: Programming Language :: Python :: 3
Classifier: Programming Language :: Python :: 3.9
Classifier: Programming Language :: Python :: 3.10
Classifier: Programming Language :: Python :: 3.11
Classifier: Programming Language :: Python :: 3.12
Requires-Dist: loguru (>=0.7.2,<0.8.0)
Requires-Dist: typer-slim (>=0.13.0,<0.14.0)
